openbb/__init__.py
openbb/assets/reference.json
openbb/main.py
openbb/package/__extensions__.py
openbb/package/__init__.py
openbb/package/empty.py
openbb/py.typed
openbb/utils.py
openbb_empty-1.0.1.dist-info/METADATA
openbb_empty-1.0.1.dist-info/WHEEL
openbb_empty-1.0.1.dist-info/entry_points.txt
openbb_empty-1.0.1.dist-info/RECORD
