Metadata-Version: 2.1
Name: openbb-empty
Version: 1.0.1
Summary: An Empty OpenBB Configuration.
Author: deeleeramone
Author-email: hello@openbb.co
Requires-Python: >=3.10,<3.13
Classifier: Programming Language :: Python :: 3
Classifier: Programming Language :: Python :: 3.10
Classifier: Programming Language :: Python :: 3.11
Classifier: Programming Language :: Python :: 3.12
Provides-Extra: all
Provides-Extra: charting
Provides-Extra: notebook
Provides-Extra: pywry
Requires-Dist: jedi-language-server (>=0.41,<0.42) ; extra == "notebook" or extra == "all"
Requires-Dist: nbclassic (>=1.1,<2.0) ; extra == "notebook" or extra == "all"
Requires-Dist: notebook (>=7.2,<8.0) ; extra == "notebook" or extra == "all"
Requires-Dist: openbb-charting (>=2.2.0,<3.0.0) ; extra == "charting" or extra == "all"
Requires-Dist: openbb-core (>=1.3.0,<2.0.0)
Requires-Dist: openbb-devtools (>=1.3.0,<2.0.0)
Requires-Dist: pywry (>=0.6.2,<0.7.0) ; extra == "pywry" or extra == "all"
